pytest_chronicle/__init__.py
pytest_chronicle/backfill.py
pytest_chronicle/config.py
pytest_chronicle/export_sqlite.py
pytest_chronicle/import_sqlite.py
pytest_chronicle/ingest.py
pytest_chronicle/models.py
pytest_chronicle/pytest_plugin.py
pytest_chronicle/alembic/env.py
pytest_chronicle/alembic/script.py.mako
pytest_chronicle/alembic/versions/20250917_0001_init.py
pytest_chronicle/alembic/versions/20250917_0002_indexes_and_jsonb.py
pytest_chronicle/backends/__init__.py
pytest_chronicle/backends/base.py
pytest_chronicle/backends/sql.py
pytest_chronicle/cli/__init__.py
pytest_chronicle/cli/__main__.py
pytest_chronicle/cli/backfill_cmd.py
pytest_chronicle/cli/config_cmd.py
pytest_chronicle/cli/db_cmd.py
pytest_chronicle/cli/export_sqlite_cmd.py
pytest_chronicle/cli/import_sqlite_cmd.py
pytest_chronicle/cli/ingest_cmd.py
pytest_chronicle/cli/init_cmd.py
pytest_chronicle/cli/query_cmd.py
pytest_chronicle/cli/run_cmd.py
pytest_chronicle-0.4.6.dist-info/licenses/LICENSE
pytest_chronicle-0.4.6.dist-info/METADATA
pytest_chronicle-0.4.6.dist-info/WHEEL
pytest_chronicle-0.4.6.dist-info/entry_points.txt
pytest_chronicle-0.4.6.dist-info/top_level.txt
pytest_chronicle-0.4.6.dist-info/RECORD
