Metadata-Version: 2.4
Name: pytest-chronicle
Version: 0.4.6
Summary: Reusable pytest results ingestion tooling with database export and CLI helpers.
Author: Survi Team
License-Expression: MIT
Requires-Python: >=3.12
License-File: LICENSE
Requires-Dist: sqlalchemy>=2.0
Requires-Dist: sqlmodel>=0.0.24
Requires-Dist: aiosqlite>=0.20
Requires-Dist: asyncpg>=0.29
Requires-Dist: alembic>=1.13
Requires-Dist: rich>=13.7
Provides-Extra: dev
Requires-Dist: pytest>=8.0; extra == "dev"
Requires-Dist: pytest-asyncio>=0.23; extra == "dev"
Requires-Dist: pytest-cov>=4.0; extra == "dev"
Requires-Dist: ruff>=0.6; extra == "dev"
Dynamic: license-file
